minimax_client-0.6.2.dist-info/METADATA
minimax_client-0.6.2.dist-info/WHEEL
minimax_client-0.6.2.dist-info/entry_points.txt
minimax_client-0.6.2.dist-info/licenses/LICENSE.md
minimax_client/__init__.py
minimax_client/__version__.py
minimax_client/client.py
minimax_client/entities/__init__.py
minimax_client/entities/assistant.py
minimax_client/entities/audio.py
minimax_client/entities/chat_completion.py
minimax_client/entities/common.py
minimax_client/entities/embedding.py
minimax_client/entities/file.py
minimax_client/entities/fine_tuning.py
minimax_client/entities/retrieval.py
minimax_client/entities/thread.py
minimax_client/interfaces/__init__.py
minimax_client/interfaces/assistant.py
minimax_client/interfaces/audio.py
minimax_client/interfaces/base.py
minimax_client/interfaces/chat_completion.py
minimax_client/interfaces/embedding.py
minimax_client/interfaces/file.py
minimax_client/interfaces/fine_tuning.py
minimax_client/interfaces/retrieval.py
minimax_client/interfaces/thread.py
minimax_client-0.6.2.dist-info/RECORD
