Metadata-Version: 2.1
Name: minimax-client
Version: 0.6.2
Summary: An (unofficial) python native client for easy interaction with MiniMax Open Platform
Keywords: web,ai,api,llm,nlp,minimax
Author-Email: Zeyang Lin <4020306+linzeyang@users.noreply.github.com>
License: MIT
Classifier: Development Status :: 3 - Alpha
Classifier: License :: OSI Approved :: MIT License
Classifier: Intended Audience :: Developers
Classifier: Natural Language :: English
Classifier: Operating System :: Microsoft :: Windows
Classifier: Operating System :: POSIX :: Linux
Classifier: Programming Language :: Python
Classifier: Programming Language :: Python :: 3
Classifier: Programming Language :: Python :: 3 :: Only
Classifier: Programming Language :: Python :: 3.8
Classifier: Programming Language :: Python :: 3.9
Classifier: Programming Language :: Python :: 3.10
Classifier: Programming Language :: Python :: 3.11
Classifier: Programming Language :: Python :: 3.12
Classifier: Programming Language :: Python :: 3.13
Classifier: Programming Language :: Python :: Implementation :: CPython
Classifier: Topic :: Internet :: WWW/HTTP
Classifier: Typing :: Typed
Project-URL: Homepage, https://pypi.org/project/minimax-client/
Project-URL: Repository, https://github.com/linzeyang/minimax-python-client
Requires-Python: >=3.8
Requires-Dist: httpx<1
Requires-Dist: python-dotenv<2
Requires-Dist: pydantic<3
Provides-Extra: dev
Requires-Dist: pytest<9,>=8.3; extra == "dev"
